{
  "projects": [
    {
      "name": "Daily routines",
      "createdAt": 1700290861039,
      "updatedAt": null,
      "id": 1
    },
    {
      "name": "Programming",
      "createdAt": 1700291084476,
      "updatedAt": null,
      "id": 2
    },
    {
      "name": "test",
      "createdAt": 1721808402484,
      "id": 3
    },
    {
      "name": "as",
      "createdAt": 1721808432622,
      "id": 4
    }
  ],
  "tasks": [
    {
      "id": 1,
      "projectId": "1",
      "name": "Angular v16 !!!",
      "done": false,
      "createdAt": 1693042928127,
      "updatedAt": 1697740416385,
      "project": "",
      "description": "Learn angular\n"
    },
    {
      "name": "Learn forms",
      "projectId": "2",
      "done": true,
      "createdAt": 1697281707175,
      "id": 4,
      "updatedAt": 1697883806405,
      "project": "",
      "description": "Learn reactive forms\n"
    },
    {
      "name": "Plant trees",
      "description": "",
      "done": false,
      "createdAt": 1721721495916,
      "projectId": 1,
      "id": 5
    }
  ]
}